odoo/addons/sale_order_weight/README.rst
odoo/addons/sale_order_weight/__init__.py
odoo/addons/sale_order_weight/__manifest__.py
odoo/addons/sale_order_weight/pre_init_hook.py
odoo/addons/sale_order_weight/i18n/es.po
odoo/addons/sale_order_weight/i18n/fr.po
odoo/addons/sale_order_weight/i18n/pt.po
odoo/addons/sale_order_weight/i18n/sale_order_weight.pot
odoo/addons/sale_order_weight/models/__init__.py
odoo/addons/sale_order_weight/models/sale_order.py
odoo/addons/sale_order_weight/models/sale_order_line.py
odoo/addons/sale_order_weight/readme/CONTRIBUTORS.rst
odoo/addons/sale_order_weight/readme/DESCRIPTION.rst
odoo/addons/sale_order_weight/static/description/icon.png
odoo/addons/sale_order_weight/static/description/index.html
odoo/addons/sale_order_weight/tests/__init__.py
odoo/addons/sale_order_weight/tests/test_sale_order_weight.py
odoo/addons/sale_order_weight/views/sale_order_view.xml
odoo12_addon_sale_order_weight-12.0.1.1.0.dist-info/METADATA
odoo12_addon_sale_order_weight-12.0.1.1.0.dist-info/WHEEL
odoo12_addon_sale_order_weight-12.0.1.1.0.dist-info/top_level.txt
odoo12_addon_sale_order_weight-12.0.1.1.0.dist-info/RECORD
